rocraters-0.4.7.dist-info/METADATA
rocraters-0.4.7.dist-info/WHEEL
rocraters/__init__.py
rocraters/rocraters.cpython-313-x86_64-linux-gnu.so
rocraters-0.4.7.dist-info/RECORD
