Metadata-Version: 2.4
Name: rocraters
Version: 0.4.7
Classifier: Programming Language :: Rust
Classifier: Programming Language :: Python :: Implementation :: CPython
Classifier: Programming Language :: Python :: Implementation :: PyPy
Classifier: Development Status :: 2 - Pre-Alpha
Classifier: Programming Language :: Python :: 3.10
Classifier: Programming Language :: Python :: 3.11
Classifier: Programming Language :: Python :: 3.12
Classifier: Programming Language :: Python :: 3.13
Summary: Lightweight Python library for RO-Crate manipulation implemented in Rust
Keywords: ro-crate,rocrate,research object,rocraters
Author: Matt Burridge <m.burridge1@newcastle.ac.uk>
Author-email: Matt Burridge <m.burridge1@newcastle.ac.uk>
License: Apache-2.0
Requires-Python: >=3.10
